{
  "experiment": "cross_length",
  "model_type": "lamar",
  "variant": "random",
  "pair_name": "SF3A3_HepG2_ENCSR331MIC",
  "pretrain_path": "",
  "max_length": 1024,
  "n_folds": 5,
  "hyperparameters": {
    "learning_rate": 5e-05,
    "per_device_train_batch_size": 16,
    "weight_decay": 0.01,
    "warmup_ratio": 0.1,
    "num_train_epochs": 10,
    "gradient_accumulation_steps": 1,
    "early_stopping_patience": 3
  },
  "cv_metrics": {
    "epoch_mean": 9.8,
    "epoch_std": 0.4,
    "eval_accuracy_mean": 0.794078947368421,
    "eval_accuracy_std": 0.017969079320720612,
    "eval_auc_mean": 0.829485688462252,
    "eval_auc_std": 0.01412458268339952,
    "eval_auprc_mean": 0.6506886038984245,
    "eval_auprc_std": 0.04413661038718777,
    "eval_f1_mean": 0.6002953181671908,
    "eval_f1_std": 0.033635248248915346,
    "eval_loss_mean": 0.4568043053150177,
    "eval_loss_std": 0.02666565852912233,
    "eval_matthews_correlation_mean": 0.4679381873888719,
    "eval_matthews_correlation_std": 0.043079212874022485,
    "eval_precision_mean": 0.6474510673879926,
    "eval_precision_std": 0.06278414168660613,
    "eval_recall_mean": 0.5672449008989432,
    "eval_recall_std": 0.06156923709404512,
    "eval_runtime_mean": 6.540699999999999,
    "eval_runtime_std": 0.0070290824436763455,
    "eval_samples_per_second_mean": 48.527,
    "eval_samples_per_second_std": 0.05867537814109151,
    "eval_steps_per_second_mean": 3.0574000000000003,
    "eval_steps_per_second_std": 0.0032000000000000028
  },
  "cv_fold_metrics": [
    {
      "eval_loss": 0.4403035640716553,
      "eval_accuracy": 0.819078947368421,
      "eval_f1": 0.6153846153846153,
      "eval_precision": 0.7586206896551724,
      "eval_recall": 0.5176470588235295,
      "eval_auc": 0.8428686543110395,
      "eval_auprc": 0.7274699893015237,
      "eval_matthews_correlation": 0.5182484435770097,
      "eval_runtime": 6.5464,
      "eval_samples_per_second": 48.577,
      "eval_steps_per_second": 3.055,
      "epoch": 10.0
    },
    {
      "eval_loss": 0.4583728313446045,
      "eval_accuracy": 0.7763157894736842,
      "eval_f1": 0.5342465753424657,
      "eval_precision": 0.609375,
      "eval_recall": 0.47560975609756095,
      "eval_auc": 0.8362997143484948,
      "eval_auprc": 0.6224635327030202,
      "eval_matthews_correlation": 0.39517641137018855,
      "eval_runtime": 6.5458,
      "eval_samples_per_second": 48.581,
      "eval_steps_per_second": 3.055,
      "epoch": 10.0
    },
    {
      "eval_loss": 0.5077598094940186,
      "eval_accuracy": 0.7730263157894737,
      "eval_f1": 0.6057142857142856,
      "eval_precision": 0.5760869565217391,
      "eval_recall": 0.6385542168674698,
      "eval_auc": 0.8029766123316796,
      "eval_auprc": 0.595668201630028,
      "eval_matthews_correlation": 0.4481195806325176,
      "eval_runtime": 6.537,
      "eval_samples_per_second": 48.493,
      "eval_steps_per_second": 3.059,
      "epoch": 10.0
    },
    {
      "eval_loss": 0.44299086928367615,
      "eval_accuracy": 0.8092105263157895,
      "eval_f1": 0.6233766233766234,
      "eval_precision": 0.6666666666666666,
      "eval_recall": 0.5853658536585366,
      "eval_auc": 0.8276752362118215,
      "eval_auprc": 0.6540415010270633,
      "eval_matthews_correlation": 0.49822573688876715,
      "eval_runtime": 6.5458,
      "eval_samples_per_second": 48.428,
      "eval_steps_per_second": 3.055,
      "epoch": 10.0
    },
    {
      "eval_loss": 0.43459445238113403,
      "eval_accuracy": 0.7927631578947368,
      "eval_f1": 0.6227544910179641,
      "eval_precision": 0.6265060240963856,
      "eval_recall": 0.6190476190476191,
      "eval_auc": 0.8376082251082251,
      "eval_auprc": 0.6537997948304873,
      "eval_matthews_correlation": 0.47992076447587634,
      "eval_runtime": 6.5285,
      "eval_samples_per_second": 48.556,
      "eval_steps_per_second": 3.063,
      "epoch": 9.0
    }
  ],
  "test_metrics": {
    "eval_loss": 0.7060047388076782,
    "eval_accuracy": 0.7060406698564593,
    "eval_f1": 0.6269449715370019,
    "eval_precision": 0.785171102661597,
    "eval_recall": 0.52179406190777,
    "eval_auc": 0.7752995968307503,
    "eval_auprc": 0.7262114727658968,
    "eval_matthews_correlation": 0.4230612192538466,
    "eval_runtime": 72.1023,
    "eval_samples_per_second": 46.448,
    "eval_steps_per_second": 2.913,
    "epoch": 5.0
  }
}