{
  "experiment": "rbp",
  "model_type": "lamar",
  "variant": "lamar_tapt_512",
  "rbp_name": "HNRNPK_K562_200",
  "weights_path": "/gpfs/bwfor/work/ws/fr_ml642-thesis_work/Thesis/LAMAR/src/pretrain/saving_model/tapt_lamar/checkpoint-98000",
  "max_length": 512,
  "n_folds": 5,
  "hyperparameters": {
    "learning_rate": 5e-05,
    "per_device_train_batch_size": 16,
    "weight_decay": 0.01,
    "warmup_ratio": 0.1,
    "num_train_epochs": 10,
    "gradient_accumulation_steps": 1,
    "early_stopping_patience": 3
  },
  "cv_metrics": {
    "epoch_mean": 8.6,
    "epoch_std": 1.4966629547095764,
    "eval_accuracy_mean": 0.9388646288209607,
    "eval_accuracy_std": 0.0024894659936662215,
    "eval_auc_mean": 0.9853453956828687,
    "eval_auc_std": 0.0026137567376007345,
    "eval_auprc_mean": 0.9846059304382013,
    "eval_auprc_std": 0.0036741902527508224,
    "eval_f1_mean": 0.9396261372276417,
    "eval_f1_std": 0.0022766289490794974,
    "eval_loss_mean": 0.20054369270801545,
    "eval_loss_std": 0.01868362446375237,
    "eval_matthews_correlation_mean": 0.8786730569097857,
    "eval_matthews_correlation_std": 0.004576217804012793,
    "eval_precision_mean": 0.927449745904984,
    "eval_precision_std": 0.016724497125857673,
    "eval_recall_mean": 0.9527648514614965,
    "eval_recall_std": 0.017723612315785453,
    "eval_runtime_mean": 7.5682,
    "eval_runtime_std": 0.006154997969130619,
    "eval_samples_per_second_mean": 121.03299999999999,
    "eval_samples_per_second_std": 0.09861034428496776,
    "eval_steps_per_second_mean": 7.6636,
    "eval_steps_per_second_std": 0.006280127387243076
  },
  "cv_fold_metrics": [
    {
      "eval_loss": 0.19368749856948853,
      "eval_accuracy": 0.9388646288209607,
      "eval_f1": 0.9404255319148936,
      "eval_precision": 0.9151138716356108,
      "eval_recall": 0.9671772428884027,
      "eval_matthews_correlation": 0.8791612563256725,
      "eval_auc": 0.9864132377969422,
      "eval_auprc": 0.9859399811109579,
      "eval_runtime": 7.5615,
      "eval_samples_per_second": 121.14,
      "eval_steps_per_second": 7.67,
      "epoch": 9.0
    },
    {
      "eval_loss": 0.21574044227600098,
      "eval_accuracy": 0.9377729257641921,
      "eval_f1": 0.9367369589345172,
      "eval_precision": 0.9504504504504504,
      "eval_recall": 0.9234135667396062,
      "eval_matthews_correlation": 0.8758905010908931,
      "eval_auc": 0.9861701062627823,
      "eval_auprc": 0.9855091814794402,
      "eval_runtime": 7.5724,
      "eval_samples_per_second": 120.966,
      "eval_steps_per_second": 7.659,
      "epoch": 8.0
    },
    {
      "eval_loss": 0.20096296072006226,
      "eval_accuracy": 0.9432314410480349,
      "eval_f1": 0.9429824561403509,
      "eval_precision": 0.945054945054945,
      "eval_recall": 0.9409190371991247,
      "eval_matthews_correlation": 0.8864697106384425,
      "eval_auc": 0.9853167622507306,
      "eval_auprc": 0.9836412198946516,
      "eval_runtime": 7.5604,
      "eval_samples_per_second": 121.158,
      "eval_steps_per_second": 7.672,
      "epoch": 10.0
    },
    {
      "eval_loss": 0.16943460702896118,
      "eval_accuracy": 0.9388646288209607,
      "eval_f1": 0.940552016985138,
      "eval_precision": 0.9152892561983471,
      "eval_recall": 0.9672489082969432,
      "eval_matthews_correlation": 0.8791470008114756,
      "eval_auc": 0.9883249747335101,
      "eval_auprc": 0.9895893504084882,
      "eval_runtime": 7.5759,
      "eval_samples_per_second": 120.909,
      "eval_steps_per_second": 7.656,
      "epoch": 6.0
    },
    {
      "eval_loss": 0.22289295494556427,
      "eval_accuracy": 0.9355895196506551,
      "eval_f1": 0.9374337221633086,
      "eval_precision": 0.911340206185567,
      "eval_recall": 0.9650655021834061,
      "eval_matthews_correlation": 0.8726968156824451,
      "eval_auc": 0.9805018973703782,
      "eval_auprc": 0.9783499192974684,
      "eval_runtime": 7.5708,
      "eval_samples_per_second": 120.992,
      "eval_steps_per_second": 7.661,
      "epoch": 10.0
    }
  ],
  "test_metrics": {
    "eval_loss": 0.2367984801530838,
    "eval_accuracy": 0.9301919720767888,
    "eval_f1": 0.9281867145421903,
    "eval_precision": 0.9609665427509294,
    "eval_recall": 0.8975694444444444,
    "eval_matthews_correlation": 0.8623257200179549,
    "eval_auc": 0.9827454922027291,
    "eval_auprc": 0.9806626415517654,
    "eval_runtime": 9.4594,
    "eval_samples_per_second": 121.15,
    "eval_steps_per_second": 7.612,
    "epoch": 8.0
  }
}